{
  "config": {
    "step": {
      "user": {
        "title": "Настройка Beurer BF 700",
        "description": "Выберите весы из списка обнаруженных устройств",
        "data": {
          "mac_address": "Устройство"
        }
      }
    },
    "error": {
      "cannot_connect": "Не удалось подключиться к весам",
      "unknown": "Неизвестная ошибка"
    },
    "abort": {
      "already_configured": "Это устройство уже добавлено",
      "no_devices_found": "Не найдено устройств Beurer. Убедитесь, что Bluetooth включён и весы в режиме сопряжения"
    }
  }
}
